{
  "BTN": {
    "bulkInsert": "Importer",
    "cancel": "Annuler",
    "close": "Fermer",
    "ok": "Confirmer",
    "remove": "Supprimer",
    "save": "Sauvegarder",
    "submit": "Soumettre"
  },
  "DIALOG": {
    "ERROR": {
      "aboutErrorText": "une erreur inattendue est apparue",
      "code": "Code d'erreur",
      "pleaseDescribePlaceholder": "Veuillez décrire quelles actions ont provoqué cette erreur, afin que nous puissions le réparer plus rapidement",
      "safeRestart": "Redémarrage en toute sécurité",
      "title": "Oups ... mon erreur."
    },
    "EXIT": {
      "justExit": "Se déconnecter",
      "makeSureYouSaved": "Veuillez vous assurer que toutes les données sont enregistrées",
      "saveExit": "Sauvegarder et quitter",
      "title": "Sortie"
    }
  },
  "EDITOR": {
    "BTN": {
      "groupsAndDiscounts": "Groupes et réductions",
      "item": "Élément",
      "proceed": "Insérer",
      "save": "Sauvegarder",
      "setup": "Installation",
      "setupAddItem": "Ajouter un item"
    },
    "ERROR": {
      "no_data": "Aucune donnée pour l'insertion détectée",
      "not_enough_cols": "Il y a moins de colonnes sur le presse-papiers que vous avez sélectionné ci-dessus",
      "too_many_cols": "Il y a plus de colonnes sur le presse-papiers que vous avez sélectionné ci-dessus"
    },
    "GRID": {
      "Brand": "Fabricante",
      "IID": "Iid",
      "Title": "Nom",
      "addRange": "Ajouter la plage",
      "appendText": "Texte supplémentaire",
      "asCoefficient": "coefficient",
      "itemForCertainAmountCheckbox": "Quantité disponible",
      "range": "Gamme",
      "rangeFrom": "DEPUIS",
      "rangeTo": "POUR",
      "value": "Valeur",
      "valueDepOnAmount": "Coût en fonction de la quantité"
    },
    "PLCH": {
      "addDiscountGroup": "Ajouter le modificateur de groupe",
      "addGroup": "Ajouter un groupe",
      "addPlan": "Ajouter un plan",
      "textToAppend": "Texte supplémentaire"
    },
    "TEXT": {
      "clickAndPaste": "Mettez en surbrillance la zone d'insertion (jaune) et appuyez sur Ctrl-V sur votre clavier",
      "clickHere": "Cliquez ici",
      "pasteZone": "Zone d'insertion",
      "pressCTRLV": "Appuyez sur Ctrl-V",
      "specifyOrder": "Cochez les colonnes (cases à cocher) que vous insérez et les définissez dans l'ordre (glisser-déposer)"
    },
    "TTL": {
      "addSelectedItems": "Ajouter des éléments sélectionnés",
      "discountGroups": "Modificateurs de valeur",
      "discountMarkup": "Remise / balisage pourcentage",
      "discountPercent": "Pourcentage de remise / balisage",
      "discountPlans": "Plans de réduction",
      "groupIsForStructure": "Groupe de structure",
      "groups": "Groupes d'éléments",
      "insertFromClipboard": "Insertion de données à partir de tables (via le presse-papiers)",
      "itemsCount": "Count les articles",
      "newDiscountGroup": "Nouveau modificateur de groupe",
      "newDiscountPlan": "Nouveau plan",
      "newItemsGroup": "Nouveau groupe",
      "removeSelectedItems": "Supprimer sélectionné du groupe"
    },
    "TTP": {
      "exit": "Sortie",
      "redo": "Répéter",
      "undo": "Annuler",
      "updatePrice": "Mettre à jour le prix"
    },
    "TYPE": {
      "item": "Élément",
      "manyitem": "Éléments",
      "manysetup": "Configurations",
      "manysetupItem": "Éléments des configurations",
      "setup": "Construire",
      "setupItem": "Élément de configuration"
    },
    "detectedRowsCountPressProceed": "Lignes détectées - {{count}}. Appuyez sur le bouton «Procéder» pour insérer des données dans le tableau"
  },
  "ERROR": {
    "check_fields_correctness": "Veuillez vérifier si tous les champs sont remplis correctement",
    "missingTranslation": "<< non traduit >>",
    "prices_went_wrong": "Erreur imprévisible"
  },
  "GRID": {
    "AND": "ET",
    "IID": "Iid",
    "OR": "OU",
    "_id": "Éléments",
    "art": "Art.",
    "autoAdd": "Montant automatique",
    "brand": "Fabricante",
    "currency": "Monnaie",
    "groups": "Groupes",
    "setFilter": "trouvée",
    "title": "Nom",
    "units": "Unités",
    "value": "Valeur"
  },
  "GRIDCTX": {
    "addItemsAfter": "Après ça",
    "addItemsBefore": "Avant ça",
    "addSelectedItemsToSetups": "Ajouter des éléments sélectionnés aux assemblages sélectionnés",
    "addSetupsAfter": "Après ça",
    "addSetupsBefore": "Avant ça",
    "clipboardElements": "Presse-papiers",
    "copy": "Copie",
    "createItem": "Créer un élément",
    "createSetup": "Créer un assemblage",
    "cut": "Couper",
    "deselectAll": "Tout déselectionner",
    "down": "Bas",
    "excelExport": "Exporter vers Excel",
    "export": "Exporter",
    "importItems": "Importer",
    "invertSelection": "Sélection inverse",
    "move": "Déplacer",
    "pasteAfter": "Insérer après",
    "pasteBefore": "Insérer avant",
    "pasteInto": "Insérer dans",
    "remove": "Supprimer",
    "selection": "Sélection",
    "sortAsc": "Trier par ordre croissant",
    "sortDesc": "Trier par ordre décroissant",
    "up": "En haut"
  },
  "GRIDDEF": {
    "andCondition": "И",
    "applyFilter": "Appliquer",
    "area": "Carré",
    "areaChart": "Carré",
    "areaGroup": "Carré",
    "ariaChecked": "vérifié",
    "ariaColumnGroupToggleVisibility": "Groupe de colonnes basculer la visibilité",
    "ariaColumnSelectAll": "Basculer toutes les colonnes",
    "ariaColumnToggleVisibility": "Visibilité de bascule de colonne",
    "ariaDateFilterInput": "Entrée de filtre à date",
    "ariaFilterColumnsInput": "Entrée des colonnes de filtre",
    "ariaFilterFromValue": "Filtre de la valeur",
    "ariaFilterInput": "Entrée de filtre",
    "ariaFilterToValue": "Filtre à valeur",
    "ariaFilterValue": "Valeur de filtre",
    "ariaFilteringOperator": "Filtrage",
    "ariaHidden": "cachée",
    "ariaIndeterminate": "indéterminée",
    "ariaInputEditor": "Éditeur d'entrée",
    "ariaRowDeselect": "Appuyez sur l'espace pour désélectionner cette ligne",
    "ariaRowSelect": "Appuyez sur l'espace pour sélectionner cette ligne",
    "ariaRowSelectAll": "Appuyez sur l'espace pour basculer toutes les lignes",
    "ariaRowToggleSelection": "Appuyez sur l'espace pour basculer la sélection des lignes",
    "ariaSearch": "Recherche",
    "ariaSearchFilterValues": "Rechercher les valeurs du filtre",
    "ariaUnchecked": "incontrôlée",
    "ariaVisible": "visible",
    "automatic": "Automatique",
    "autosizeAllColumns": "Réinitialiser les largeurs de colonne",
    "autosizeThiscolumn": "Largeur de colonne automatique",
    "avg": "Moyenne",
    "axis": "Axe",
    "background": "Arrière-plan",
    "barChart": "Bar",
    "barGroup": "Bar",
    "blanks": "(Blanks)",
    "blur": "Se brouiller",
    "bold": "Gras",
    "boldItalic": "Gras italique",
    "bottom": "Bas",
    "bubble": "Bulle",
    "bubbleTooltip": "Bulle",
    "callout": "Faire appel à",
    "cancelFilter": "Annuler",
    "categories": "Catégories",
    "category": "Catégorie",
    "chart": "Graphique",
    "chartDownloadToolbarTooltip": "Téléchargement",
    "chartLinkToolbarTooltip": "Lié à la grille",
    "chartRange": "Gamme de graphiques",
    "chartSettingsToolbarTooltip": "Menu",
    "chartUnlinkToolbarTooltip": "Sébrané de la grille",
    "clearFilter": "Claire",
    "collapseAll": "S'effondrer tout",
    "color": "Couleur",
    "columnChart": "Colonne",
    "columnGroup": "Colonne",
    "columns": "Colonnes",
    "contains": "Contient",
    "copy": "Copie",
    "copyWithHeaders": "Copier avec les en-têtes",
    "count": "Compter",
    "csvExport": "Exportation de CSV",
    "ctrlC": "Ctrl + c",
    "ctrlV": "Ctrl + v",
    "data": "Données",
    "dateFilter": "Filtre à date",
    "dateFormatOoo": "yyyyy-mm-dd",
    "defaultCategory": "(Aucune)",
    "doughnut": "Donut",
    "doughnutTooltip": "Donut",
    "empty": "Choisissez-en un",
    "enabled": "Activé",
    "endsWith": "Fini à",
    "equals": "Également",
    "excelExport": "Excel Export (.xlsx)",
    "excelXmlExport": "Excel Export (.xml)",
    "expandAll": "Divulguer tout",
    "export": "Exporter",
    "fillOpacity": "Remplir l'opacité",
    "filterOoo": "Filtre...",
    "filteredRows": "Filtrée",
    "filters": "Filtres",
    "firstPage": "Première page",
    "font": "Police de caractère",
    "format": "Format",
    "greaterThan": "Plus que",
    "greaterThanOrEqual": "Plus grand ou égal à",
    "group": "Groupe",
    "groupBy": "Par groupe",
    "groupedAreaTooltip": "Zone",
    "groupedBar": "Groupé",
    "groupedBarTooltip": "Groupé",
    "groupedColumn": "Groupé",
    "groupedColumnTooltip": "Groupé",
    "groups": "Groupes de rangs",
    "height": "Hauteur",
    "histogramBinCount": "Dénombrement des poubelles",
    "histogramChart": "Histogramme",
    "histogramGroup": "Histogramme",
    "histogramTooltip": "Histogramme",
    "inRange": "Dans la gamme",
    "inRangeEnd": "DEPUIS",
    "inRangeStart": "pour",
    "italic": "Italique",
    "itemPaddingX": "Rembourrage d'article x",
    "itemPaddingY": "Rembourrage d'article y",
    "itemSpacing": "Espacement des articles",
    "labels": "Étiquettes",
    "lastPage": "Dernière page",
    "layoutHorizontalSpacing": "Espacement horizontal",
    "layoutVerticalSpacing": "Espacement vertical",
    "left": "Gauche",
    "legend": "Légende",
    "length": "Longueur",
    "lessThan": "Moins que.",
    "lessThanOrEqual": "Moins ou égal",
    "line": "Doubler",
    "lineGroup": "Doubler",
    "lineTooltip": "Doubler",
    "lineWidth": "Largeur de ligne",
    "loadingOoo": "Chargement...",
    "markerPadding": "Rembourrage de marqueur",
    "markerSize": "Taille de marqueur",
    "markerStroke": "Coup de marqueur",
    "markers": "Marqueuses",
    "max": "Max",
    "maxSize": "Taille maximum",
    "min": "min",
    "minSize": "Taille minimale",
    "more": "Plus",
    "navigator": "Navigatrice",
    "nextPage": "Page suivante",
    "noDataToChart": "Aucune donnée disponible pour être tracée.",
    "noMatches": "Pas de correspondance",
    "noPin": "Pas d'épingle",
    "noRowsToShow": "Pas de lignes à montrer",
    "none": "Aucune",
    "normal": "Normale",
    "normalizedArea": "100% empilé",
    "normalizedAreaTooltip": "100% empilé",
    "normalizedBar": "100% empilé",
    "normalizedBarTooltip": "100% empilé",
    "normalizedColumn": "100% empilé",
    "normalizedColumnTooltip": "100% empilé",
    "notContains": "Ne contient pas",
    "notEqual": "Inégal",
    "number": "Nombre",
    "numberFilter": "Filtre numéro",
    "of": "de",
    "offset": "Compenser",
    "offsets": "Décalage",
    "orCondition": "OU",
    "padding": "Rembourrage",
    "page": "Page",
    "paired": "Mode apparié",
    "paste": "Pâte",
    "pie": "Tarte",
    "pieChart": "Tarte",
    "pieGroup": "Tarte",
    "pieTooltip": "Tarte",
    "pinColumn": "Colonne d'épingle",
    "pinLeft": "Épingle à gauche",
    "pinRight": "Épingler à droite",
    "pivotChart": "Graphique de pivot",
    "pivotChartAndPivotMode": "Tableau de pivot et mode pivot",
    "pivotChartRequiresPivotMode": "Le graphique de pivot nécessite le mode pivot activé.",
    "pivotChartTitle": "Graphique de pivot",
    "pivotColumnsEmptyMessage": "Faites glisser ici pour définir les étiquettes de colonne",
    "pivotMode": "Mode pivot",
    "pivots": "Étiquettes de colonne",
    "position": "Position",
    "predefined": "Prédéfinie",
    "previousPage": "Page précédente",
    "rangeChartTitle": "Diagramme de plage",
    "resetColumns": "Réinitialiser les colonnes",
    "resetFilter": "Réinitialiser",
    "right": "Droite",
    "rowGroupColumnsEmptyMessage": "Faites glisser ici pour définir des groupes de lignes",
    "scatter": "Dispersion",
    "scatterGroup": "X y (dispersion)",
    "scatterTooltip": "Dispersion",
    "searchOoo": "Recherche...",
    "selectAll": "(Tout sélectionner)",
    "selectAllSearchResults": "(Sélectionnez tous les résultats de recherche)",
    "selectedRows": "Choisie",
    "series": "Série",
    "setFilter": "Set filtre",
    "settings": "Paramètres",
    "shadow": "Ombre",
    "size": "Taille",
    "spacing": "Espacement",
    "stackedArea": "Empilée",
    "stackedAreaTooltip": "Empilée",
    "stackedBar": "Empilée",
    "stackedBarTooltip": "Empilée",
    "stackedColumn": "Empilée",
    "stackedColumnTooltip": "Empilée",
    "startsWith": "Ça commence par",
    "strokeOpacity": "Ligne de ligne",
    "strokeWidth": "Largeur du trait",
    "sum": "Somme",
    "textFilter": "Filtre à texte",
    "thickness": "Épaisseur",
    "ticks": "Tic",
    "time": "Temps",
    "title": "Titre",
    "titlePlaceholder": "Titre du graphique - double clic pour modifier",
    "to": "pour",
    "tooltips": "Infractions",
    "top": "Haut",
    "totalAndFilteredRows": "Lignes",
    "totalRows": "Total des lignes",
    "ungroupBy": "Non-groupe par",
    "valueAggregation": "Agrégation de valeur",
    "valueColumnsEmptyMessage": "Faites glisser ici pour agréger",
    "values": "Valeurs",
    "width": "Largeur",
    "xOffset": "Décalage x",
    "xRotation": "X rotation",
    "xType": "Type x",
    "xyChart": "X y (dispersion)",
    "xyValues": "X Valeurs",
    "yOffset": "Y décalage",
    "yRotation": "R ROTATION"
  },
  "HOME": {
    "BTN": {
      "backToEditDistributor": "Retour à l'édition",
      "createEquipmentPrice": "Nouveau prix de l'équipement",
      "createGroup": "Nouveau dossier",
      "createLabourPrice": "Prix de nouveaux travaux",
      "loadPublic": "Prix",
      "previewDistributorCard": "Carte de prévisualisation",
      "resetSearch": "Réinitialiser",
      "searchOptions": "Options",
      "sharePrices": "Partage les prix"
    },
    "ERROR": {
      "fillRequired": "Veuillez remplir tous les champs requis"
    },
    "INTENT": {
      "import": "Prix d'importation",
      "importInfo": "Vous pouvez utiliser les prix importés dans vos projets, tous les articles seront mis à jour dynamiquement par le propriétaire du prix",
      "importWarn": "Importer",
      "removeImported": "Supprimer",
      "removeImportedInfo": "Vous perdrez l'accès aux listes de prix et tous les articles utilisés disparaîtront de vos estimations",
      "removeImportedWarn": "Supprimer",
      "share": "Partager le prix",
      "shareInfo": "Les prix partagés deviendront visibles pour tous les utilisateurs d'Irrisketch",
      "shareWarn": "Rendre le public",
      "stopSharing": "Supprimer de partagé",
      "stopSharingInfo": "Les prix deviendront privés et plus personne ne peut les utiliser. \n De plus, tous ses articles disparaîtront dans les dépenses des utilisateurs, donc ne faites-le que si vous êtes absolument nécessaire",
      "stopSharingWarn": "Supprimer de partagé"
    },
    "PLCH": {
      "contactNumber": "Numéro de téléphone",
      "description": "Description",
      "distributorDescription": "Tout détail supplémentaire et coordonnées, tels que les sites Web, les e-mails, les chats",
      "searchPrices": "Prix de recherche",
      "title": "Titre"
    },
    "TITLE": {
      "areYouSureRemove": "Etes-vous sûr que vous voulez supprimer",
      "areYouSureYouWantTo": "Voulez-vous vraiment",
      "cannotBeUndone": "Cette action ne peut pas être annulée! \n Tous les éléments utilisés disparaîtront des estimations déjà existantes",
      "removeTitle": "Retirer"
    },
    "TTL": {
      "approved": "Confirmé par irrisketch",
      "bySubmittingYouAgree": "En partageant vos listes de prix, vous acceptez de",
      "chooseTypeOfDistributor": "Type de compte",
      "completeThisToBeAbleToShare": "Remplissez ce formulaire pour pouvoir partager vos prix",
      "contactNumber": "Numéro de contact",
      "country": "Pays",
      "countryInfo": "Ces informations seront visibles pour tout le monde",
      "create": "Créer",
      "createDistributorAccount": "Créer un compte de distributeur",
      "description": "Description",
      "descriptionMaxChars": "Maximum 200 caractères",
      "distributorDescription": "Description",
      "distributorInfo": "Informations sur le propriétaire du prix",
      "editDescription": "Changer la description",
      "enthusiast": "Passionnée",
      "equipment": "Équipement",
      "from": "depuis",
      "labours": "Travail",
      "manufacturer": "Fabricante",
      "privacyPolicy": "Accord de l'utilisateur",
      "privatePrices": "Prix personnels",
      "publicPrices": "Prix publics",
      "published": "Publié",
      "searchIn": "Articles de prix de recherche",
      "sharedPrices": "Prix partagés",
      "stateProvince": "Région",
      "title": "Titre",
      "titleMaxChars": "MAXIMUM 60 caractères",
      "titleOfDistributor": "Titre",
      "titleOfDistributorInfo": "C'est ainsi que vos clients vous reconnaîtront",
      "typeOfDistr": "Type de compte",
      "vendor": "Distributrice",
      "workshop": "Atelier",
      "youCanEditLater": "Vous pouvez modifier ces informations plus tard"
    },
    "TTP": {
      "approved": "Distributeur approuvé",
      "clone": "Cloner",
      "editDescription": "Éditer la description",
      "editDistributorInfo": "Modifier les informations",
      "import": "Importer",
      "loadDistributor": "Prix de téléchargement",
      "remove": "Supprimer",
      "share": "Partager",
      "showAboutDistributor": "Informations sur le distributeur",
      "unshare": "Arrêter de partager",
      "updatePrices": "Catalogue de rechargement",
      "you": "Toi"
    },
    "TYPE": {
      "group": "Groupe",
      "price": "Prix"
    }
  },
  "TREE": {
    "TTL": {
      "searchArts": "Art",
      "searchBrands": "Marques",
      "searchTitles": "Titres"
    }
  },
  "TTL": {
    "catalog": "Des prix",
    "editor": "Éditrice"
  }
}
